Ex_26_05/axi4lite_regs.v
// Especificação:
//   - 4 registradores de 32 bits
//   - reg0, reg1: controle — escritos via AXI4-Lite
//   - reg2, reg3: status   — atualizados por entradas externas
//   - Mapeamento: 0x00, 0x04, 0x08, 0x0C
// ============================================================

module axi4lite_regs (
    // ── Clock e Reset ────────────────────────────────────────
    input  wire        ACLK,
    input  wire        ARESETn,       // reset ativo em nível baixo

    // ── Canal AW — Write Address ─────────────────────────────
    input  wire [31:0] S_AXI_AWADDR,
    input  wire        S_AXI_AWVALID,
    output reg         S_AXI_AWREADY,

    // ── Canal W — Write Data ─────────────────────────────────
    input  wire [31:0] S_AXI_WDATA,
    input  wire [3:0]  S_AXI_WSTRB,
    input  wire        S_AXI_WVALID,
    output reg         S_AXI_WREADY,

    // ── Canal B — Write Response ─────────────────────────────
    output reg  [1:0]  S_AXI_BRESP,
    output reg         S_AXI_BVALID,
    input  wire        S_AXI_BREADY,

    // ── Canal AR — Read Address ───────────────────────────────
    input  wire [31:0] S_AXI_ARADDR,
    input  wire        S_AXI_ARVALID,
    output reg         S_AXI_ARREADY,

    // ── Canal R — Read Data ───────────────────────────────────
    output reg  [31:0] S_AXI_RDATA,
    output reg  [1:0]  S_AXI_RRESP,
    output reg         S_AXI_RVALID,
    input  wire        S_AXI_RREADY,

    // ── Entradas externas ─────────────────────────────────────
    input  wire [31:0] reg0_din,   // mantido para padronização
    input  wire [31:0] reg1_din,   // mantido para padronização
    input  wire [31:0] reg2_din,   // status externo
    input  wire [31:0] reg3_din,   // status externo

    // ── Saídas dos registradores ──────────────────────────────
    output wire [31:0] reg0_dout,
    output wire [31:0] reg1_dout,
    output wire [31:0] reg2_dout,
    output wire [31:0] reg3_dout
);

    // ── Registradores internos ────────────────────────────────
    reg [31:0] reg0;   // controle — escrito via AXI
    reg [31:0] reg1;   // controle — escrito via AXI
    // reg2 e reg3 são combinacionais (direto de din)

    // ── Saídas contínuas ─────────────────────────────────────
    assign reg0_dout = reg0;
    assign reg1_dout = reg1;
    assign reg2_dout = reg2_din;   // status: sempre reflete a entrada
    assign reg3_dout = reg3_din;   // status: sempre reflete a entrada

    // ── Endereço de escrita capturado ─────────────────────────
    reg [31:0] aw_addr_lat;   // endereço AW travado no handshake
    reg        aw_done;       // flag: endereço AW recebido
    reg        w_done;        // flag: dado W  recebido

    // =========================================================
    // ESCRITA — canais AW e W (independentes, conforme AXI4)
    // =========================================================
    always @(posedge ACLK or negedge ARESETn) begin
        if (!ARESETn) begin
            S_AXI_AWREADY <= 1'b0;
            S_AXI_WREADY  <= 1'b0;
            S_AXI_BVALID  <= 1'b0;
            S_AXI_BRESP   <= 2'b00;
            aw_addr_lat   <= 32'h0;
            aw_done       <= 1'b0;
            w_done        <= 1'b0;
            reg0          <= 32'h0;
            reg1          <= 32'h0;
        end
        else begin

            // ── Handshake AW ──────────────────────────────────
            if (S_AXI_AWVALID && !S_AXI_AWREADY) begin
                S_AXI_AWREADY <= 1'b1;
                aw_addr_lat   <= S_AXI_AWADDR;
                aw_done       <= 1'b1;
            end else begin
                S_AXI_AWREADY <= 1'b0;
            end

            // ── Handshake W ───────────────────────────────────
            if (S_AXI_WVALID && !S_AXI_WREADY) begin
                S_AXI_WREADY <= 1'b1;
                w_done       <= 1'b1;
            end else begin
                S_AXI_WREADY <= 1'b0;
            end

            // ── Escrita no registrador quando AW e W completos ─
            if (aw_done && w_done) begin
                aw_done <= 1'b0;
                w_done  <= 1'b0;
                // Aplica strobe byte a byte
                case (aw_addr_lat[3:0])
                    4'h0: begin  // reg0 — controle
                        if (S_AXI_WSTRB[0]) reg0[ 7: 0] <= S_AXI_WDATA[ 7: 0];
                        if (S_AXI_WSTRB[1]) reg0[15: 8] <= S_AXI_WDATA[15: 8];
                        if (S_AXI_WSTRB[2]) reg0[23:16] <= S_AXI_WDATA[23:16];
                        if (S_AXI_WSTRB[3]) reg0[31:24] <= S_AXI_WDATA[31:24];
                    end
                    4'h4: begin  // reg1 — controle
                        if (S_AXI_WSTRB[0]) reg1[ 7: 0] <= S_AXI_WDATA[ 7: 0];
                        if (S_AXI_WSTRB[1]) reg1[15: 8] <= S_AXI_WDATA[15: 8];
                        if (S_AXI_WSTRB[2]) reg1[23:16] <= S_AXI_WDATA[23:16];
                        if (S_AXI_WSTRB[3]) reg1[31:24] <= S_AXI_WDATA[31:24];
                    end
                    // 0x08 e 0x0C: reg2/reg3 são status — ignora escrita
                    default: ; // endereço inválido — não altera nada
                endcase
                // Gera resposta OKAY
                S_AXI_BRESP  <= 2'b00;
                S_AXI_BVALID <= 1'b1;
            end

            // ── Handshake B ───────────────────────────────────
            if (S_AXI_BVALID && S_AXI_BREADY) begin
                S_AXI_BVALID <= 1'b0;
            end
        end
    end

    // =========================================================
    // LEITURA — canais AR e R
    // =========================================================
    always @(posedge ACLK or negedge ARESETn) begin
        if (!ARESETn) begin
            S_AXI_ARREADY <= 1'b0;
            S_AXI_RVALID  <= 1'b0;
            S_AXI_RDATA   <= 32'h0;
            S_AXI_RRESP   <= 2'b00;
        end
        else begin

            // ── Handshake AR + seleção do registrador ─────────
            if (S_AXI_ARVALID && !S_AXI_ARREADY) begin
                S_AXI_ARREADY <= 1'b1;
                S_AXI_RRESP   <= 2'b00;  // OKAY
                S_AXI_RVALID  <= 1'b1;
                case (S_AXI_ARADDR[3:0])
                    4'h0:    S_AXI_RDATA <= reg0;
                    4'h4:    S_AXI_RDATA <= reg1;
                    4'h8:    S_AXI_RDATA <= reg2_din;  // status externo
                    4'hC:    S_AXI_RDATA <= reg3_din;  // status externo
                    default: S_AXI_RDATA <= 32'hDEADBEEF; // endereço inválido
                endcase
            end else begin
                S_AXI_ARREADY <= 1'b0;
            end

            // ── Handshake R ───────────────────────────────────
            if (S_AXI_RVALID && S_AXI_RREADY) begin
                S_AXI_RVALID <= 1'b0;
            end
        end
    end

endmodule

Ex_26_05/tb_axi4lite.v
`timescale 1ns/1ps

module tb_axi4lite_regs;

    // ── Sinais de clock e reset ───────────────────────────────
    reg         ACLK;
    reg         ARESETn;

    // ── Canal AW ─────────────────────────────────────────────
    reg  [31:0] S_AXI_AWADDR;
    reg         S_AXI_AWVALID;
    wire        S_AXI_AWREADY;

    // ── Canal W ──────────────────────────────────────────────
    reg  [31:0] S_AXI_WDATA;
    reg  [3:0]  S_AXI_WSTRB;
    reg         S_AXI_WVALID;
    wire        S_AXI_WREADY;

    // ── Canal B ──────────────────────────────────────────────
    wire [1:0]  S_AXI_BRESP;
    wire        S_AXI_BVALID;
    reg         S_AXI_BREADY;

    // ── Canal AR ─────────────────────────────────────────────
    reg  [31:0] S_AXI_ARADDR;
    reg         S_AXI_ARVALID;
    wire        S_AXI_ARREADY;

    // ── Canal R ──────────────────────────────────────────────
    wire [31:0] S_AXI_RDATA;
    wire [1:0]  S_AXI_RRESP;
    wire        S_AXI_RVALID;
    reg         S_AXI_RREADY;

    // ── Entradas externas ─────────────────────────────────────
    reg  [31:0] reg0_din;
    reg  [31:0] reg1_din;
    reg  [31:0] reg2_din;
    reg  [31:0] reg3_din;

    // ── Saídas ───────────────────────────────────────────────
    wire [31:0] reg0_dout;
    wire [31:0] reg1_dout;
    wire [31:0] reg2_dout;
    wire [31:0] reg3_dout;

    // ── Contadores de pass/fail ───────────────────────────────
    integer pass_count;
    integer fail_count;

    // ── Instância do DUT ─────────────────────────────────────
    axi4lite_regs dut (
        .ACLK          (ACLK),
        .ARESETn       (ARESETn),
        .S_AXI_AWADDR  (S_AXI_AWADDR),
        .S_AXI_AWVALID (S_AXI_AWVALID),
        .S_AXI_AWREADY (S_AXI_AWREADY),
        .S_AXI_WDATA   (S_AXI_WDATA),
        .S_AXI_WSTRB   (S_AXI_WSTRB),
        .S_AXI_WVALID  (S_AXI_WVALID),
        .S_AXI_WREADY  (S_AXI_WREADY),
        .S_AXI_BRESP   (S_AXI_BRESP),
        .S_AXI_BVALID  (S_AXI_BVALID),
        .S_AXI_BREADY  (S_AXI_BREADY),
        .S_AXI_ARADDR  (S_AXI_ARADDR),
        .S_AXI_ARVALID (S_AXI_ARVALID),
        .S_AXI_ARREADY (S_AXI_ARREADY),
        .S_AXI_RDATA   (S_AXI_RDATA),
        .S_AXI_RRESP   (S_AXI_RRESP),
        .S_AXI_RVALID  (S_AXI_RVALID),
        .S_AXI_RREADY  (S_AXI_RREADY),
        .reg0_din      (reg0_din),
        .reg1_din      (reg1_din),
        .reg2_din      (reg2_din),
        .reg3_din      (reg3_din),
        .reg0_dout     (reg0_dout),
        .reg1_dout     (reg1_dout),
        .reg2_dout     (reg2_dout),
        .reg3_dout     (reg3_dout)
    );

    // ── Clock 10 ns ──────────────────────────────────────────
    initial ACLK = 0;
    always #5 ACLK = ~ACLK;

    // =========================================================
    // Tarefa: escrita AXI4-Lite
    // =========================================================
    task axi_write;
        input [31:0] addr;
        input [31:0] data;
        begin
            // Apresenta AW e W simultaneamente
            @(posedge ACLK);
            S_AXI_AWADDR  = addr;
            S_AXI_AWVALID = 1;
            S_AXI_WDATA   = data;
            S_AXI_WSTRB   = 4'hF;
            S_AXI_WVALID  = 1;
            S_AXI_BREADY  = 1;

            // Aguarda AWREADY
            @(posedge ACLK);
            while (!S_AXI_AWREADY) @(posedge ACLK);
            S_AXI_AWVALID = 0;

            // Aguarda WREADY
            while (!S_AXI_WREADY) @(posedge ACLK);
            S_AXI_WVALID = 0;

            // Aguarda resposta B
            while (!S_AXI_BVALID) @(posedge ACLK);
            @(posedge ACLK);
            S_AXI_BREADY = 0;
            #1;
        end
    endtask

    // =========================================================
    // Tarefa: leitura AXI4-Lite
    // =========================================================
    task axi_read;
        input  [31:0] addr;
        output [31:0] rdata;
        begin
            @(posedge ACLK);
            S_AXI_ARADDR  = addr;
            S_AXI_ARVALID = 1;
            S_AXI_RREADY  = 1;

            // Aguarda ARREADY
            @(posedge ACLK);
            while (!S_AXI_ARREADY) @(posedge ACLK);
            S_AXI_ARVALID = 0;

            // Aguarda dado R
            while (!S_AXI_RVALID) @(posedge ACLK);
            rdata = S_AXI_RDATA;
            @(posedge ACLK);
            S_AXI_RREADY = 0;
            #1;
        end
    endtask

    // =========================================================
    // Tarefa: verifica resultado
    // =========================================================
    task check;
        input [7:0]  num;
        input [31:0] got;
        input [31:0] expected;
        input [127:0] descricao;
        begin
            if (got === expected) begin
                $display("  [PASS] Teste %02d | %s | got=0x%08h", num, descricao, got);
                pass_count = pass_count + 1;
            end else begin
                $display("  [FAIL] Teste %02d | %s | esperado=0x%08h got=0x%08h",
                         num, descricao, expected, got);
                fail_count = fail_count + 1;
            end
        end
    endtask

    // =========================================================
    // Sequência de testes
    // =========================================================
    reg [31:0] rdata;

    initial begin
        $dumpfile("wave_axi.vcd");
        $dumpvars(0, tb_axi4lite_regs);

        // Inicializa sinais
        ARESETn       = 0;
        S_AXI_AWADDR  = 0; S_AXI_AWVALID = 0;
        S_AXI_WDATA   = 0; S_AXI_WSTRB   = 0; S_AXI_WVALID = 0;
        S_AXI_BREADY  = 0;
        S_AXI_ARADDR  = 0; S_AXI_ARVALID = 0;
        S_AXI_RREADY  = 0;
        reg0_din = 0; reg1_din = 0;
        reg2_din = 0; reg3_din = 0;
        pass_count = 0; fail_count = 0;

        $display("");
        $display("============================================================");
        $display("  Testbench — Periférico AXI4-Lite com Banco de Registradores");
        $display("============================================================");

        // ── Teste 1: Reset ────────────────────────────────────
        $display("");
        $display("── Teste 1: Aplicar reset ──");
        repeat(4) @(posedge ACLK);
        ARESETn = 1;
        @(posedge ACLK); #1;
        check(1, reg0_dout, 32'h00000000, "reg0_dout apos reset  ");
        check(1, reg1_dout, 32'h00000000, "reg1_dout apos reset  ");
        check(1, reg2_dout, 32'h00000000, "reg2_dout apos reset  ");
        check(1, reg3_dout, 32'h00000000, "reg3_dout apos reset  ");

        // ── Teste 2: Escrever reg0 via AXI ───────────────────
        $display("");
        $display("── Teste 2: Escrever 0x00000011 em reg0 (end=0x00) ──");
        axi_write(32'h00000000, 32'h00000011);
        check(2, reg0_dout, 32'h00000011, "reg0_dout apos escrita");

        // ── Teste 3: Escrever reg1 via AXI ───────────────────
        $display("");
        $display("── Teste 3: Escrever 0x00000022 em reg1 (end=0x04) ──");
        axi_write(32'h00000004, 32'h00000022);
        check(3, reg1_dout, 32'h00000022, "reg1_dout apos escrita");

        // ── Teste 4: Entrada externa reg2_din ─────────────────
        $display("");
        $display("── Teste 4: Aplicar 0x00000033 em reg2_din ──");
        reg2_din = 32'h00000033;
        @(posedge ACLK); #1;
        check(4, reg2_dout, 32'h00000033, "reg2_dout = reg2_din  ");

        // ── Teste 5: Entrada externa reg3_din ─────────────────
        $display("");
        $display("── Teste 5: Aplicar 0x00000044 em reg3_din ──");
        reg3_din = 32'h00000044;
        @(posedge ACLK); #1;
        check(5, reg3_dout, 32'h00000044, "reg3_dout = reg3_din  ");

        // ── Teste 6: Ler reg0 via AXI ─────────────────────────
        $display("");
        $display("── Teste 6: Ler reg0 via AXI (end=0x00) ──");
        axi_read(32'h00000000, rdata);
        check(6, rdata,         32'h00000011, "RDATA reg0            ");
        check(6, S_AXI_RRESP,  2'b00,        "RRESP OKAY reg0       ");

        // ── Teste 7: Ler reg1 via AXI ─────────────────────────
        $display("");
        $display("── Teste 7: Ler reg1 via AXI (end=0x04) ──");
        axi_read(32'h00000004, rdata);
        check(7, rdata,         32'h00000022, "RDATA reg1            ");
        check(7, S_AXI_RRESP,  2'b00,        "RRESP OKAY reg1       ");

        // ── Teste 8: Ler reg2 via AXI ─────────────────────────
        $display("");
        $display("── Teste 8: Ler reg2 via AXI (end=0x08) ──");
        axi_read(32'h00000008, rdata);
        check(8, rdata,         32'h00000033, "RDATA reg2            ");
        check(8, S_AXI_RRESP,  2'b00,        "RRESP OKAY reg2       ");

        // ── Teste 9: Ler reg3 via AXI ─────────────────────────
        $display("");
        $display("── Teste 9: Ler reg3 via AXI (end=0x0C) ──");
        axi_read(32'h0000000C, rdata);
        check(9, rdata,         32'h00000044, "RDATA reg3            ");
        check(9, S_AXI_RRESP,  2'b00,        "RRESP OKAY reg3       ");

        // ── Teste 10: Verificar saídas dout ───────────────────
        $display("");
        $display("── Teste 10: Verificar saidas dout ──");
        check(10, reg0_dout, 32'h00000011, "reg0_dout             ");
        check(10, reg1_dout, 32'h00000022, "reg1_dout             ");
        check(10, reg2_dout, 32'h00000033, "reg2_dout             ");
        check(10, reg3_dout, 32'h00000044, "reg3_dout             ");

        // ── Teste 11: Tentar escrever reg2 via AXI ────────────
        $display("");
        $display("── Teste 11: Tentar escrever em reg2 (end=0x08) — deve ser ignorado ──");
        axi_write(32'h00000008, 32'hDEADBEEF);
        @(posedge ACLK); #1;
        check(11, reg2_dout, 32'h00000033, "reg2 mantem reg2_din  ");

        // ── Teste 12: Tentar escrever reg3 via AXI ────────────
        $display("");
        $display("── Teste 12: Tentar escrever em reg3 (end=0x0C) — deve ser ignorado ──");
        axi_write(32'h0000000C, 32'hCAFEBABE);
        @(posedge ACLK); #1;
        check(12, reg3_dout, 32'h00000044, "reg3 mantem reg3_din  ");

        // ── Resumo ────────────────────────────────────────────
        $display("");
        $display("============================================================");
        $display("  RESUMO: %0d PASS | %0d FAIL | Total: %0d testes",
                 pass_count, fail_count, pass_count + fail_count);
        $display("============================================================");
        $display("");
        $finish;
    end

endmodule

Ex_26_05/wave_axi.vcd
$date
	Sat May 30 23:57:03 2026
$end
$version
	Icarus Verilog
$end
$timescale
	1ps
$end
$scope module tb_axi4lite_regs $end
$var wire 32 ! reg3_dout [31:0] $end
$var wire 32 " reg2_dout [31:0] $end
$var wire 32 # reg1_dout [31:0] $end
$var wire 32 $ reg0_dout [31:0] $end
$var wire 1 % S_AXI_WREADY $end
$var wire 1 & S_AXI_RVALID $end
$var wire 2 ' S_AXI_RRESP [1:0] $end
$var wire 32 ( S_AXI_RDATA [31:0] $end
$var wire 1 ) S_AXI_BVALID $end
$var wire 2 * S_AXI_BRESP [1:0] $end
$var wire 1 + S_AXI_AWREADY $end
$var wire 1 , S_AXI_ARREADY $end
$var reg 1 - ACLK $end
$var reg 1 . ARESETn $end
$var reg 32 / S_AXI_ARADDR [31:0] $end
$var reg 1 0 S_AXI_ARVALID $end
$var reg 32 1 S_AXI_AWADDR [31:0] $end
$var reg 1 2 S_AXI_AWVALID $end
$var reg 1 3 S_AXI_BREADY $end
$var reg 1 4 S_AXI_RREADY $end
$var reg 32 5 S_AXI_WDATA [31:0] $end
$var reg 4 6 S_AXI_WSTRB [3:0] $end
$var reg 1 7 S_AXI_WVALID $end
$var reg 32 8 rdata [31:0] $end
$var reg 32 9 reg0_din [31:0] $end
$var reg 32 : reg1_din [31:0] $end
$var reg 32 ; reg2_din [31:0] $end
$var reg 32 < reg3_din [31:0] $end
$var integer 32 = fail_count [31:0] $end
$var integer 32 > pass_count [31:0] $end
$scope module dut $end
$var wire 1 - ACLK $end
$var wire 1 . ARESETn $end
$var wire 32 ? S_AXI_ARADDR [31:0] $end
$var wire 1 0 S_AXI_ARVALID $end
$var wire 32 @ S_AXI_AWADDR [31:0] $end
$var wire 1 2 S_AXI_AWVALID $end
$var wire 1 3 S_AXI_BREADY $end
$var wire 1 4 S_AXI_RREADY $end
$var wire 32 A S_AXI_WDATA [31:0] $end
$var wire 4 B S_AXI_WSTRB [3:0] $end
$var wire 1 7 S_AXI_WVALID $end
$var wire 32 C reg0_din [31:0] $end
$var wire 32 D reg0_dout [31:0] $end
$var wire 32 E reg1_din [31:0] $end
$var wire 32 F reg1_dout [31:0] $end
$var wire 32 G reg2_din [31:0] $end
$var wire 32 H reg2_dout [31:0] $end
$var wire 32 I reg3_din [31:0] $end
$var wire 32 J reg3_dout [31:0] $end
$var reg 1 , S_AXI_ARREADY $end
$var reg 1 + S_AXI_AWREADY $end
$var reg 2 K S_AXI_BRESP [1:0] $end
$var reg 1 ) S_AXI_BVALID $end
$var reg 32 L S_AXI_RDATA [31:0] $end
$var reg 2 M S_AXI_RRESP [1:0] $end
$var reg 1 & S_AXI_RVALID $end
$var reg 1 % S_AXI_WREADY $end
$var reg 32 N aw_addr_lat [31:0] $end
$var reg 1 O aw_done $end
$var reg 32 P reg0 [31:0] $end
$var reg 32 Q reg1 [31:0] $end
$var reg 1 R w_done $end
$upscope $end
$scope task axi_read $end
$var reg 32 S addr [31:0] $end
$var reg 32 T rdata [31:0] $end
$upscope $end
$scope task axi_write $end
$var reg 32 U addr [31:0] $end
$var reg 32 V data [31:0] $end
$upscope $end
$scope task check $end
$var reg 128 W descricao [127:0] $end
$var reg 32 X expected [31:0] $end
$var reg 32 Y got [31:0] $end
$var reg 8 Z num [7:0] $end
$upscope $end
$upscope $end
$enddefinitions $end
$comment Show the parameter values. $end
$dumpall
$end
#0
$dumpvars
bx Z
bx Y
bx X
bx W
bx V
bx U
bx T
bx S
0R
b0 Q
b0 P
0O
b0 N
b0 M
b0 L
b0 K
b0 J
b0 I
b0 H
b0 G
b0 F
b0 E
b0 D
b0 C
b0 B
b0 A
b0 @
b0 ?
b0 >
b0 =
b0 <
b0 ;
b0 :
b0 9
bx 8
07
b0 6
b0 5
04
03
02
b0 1
00
b0 /
0.
0-
0,
0+
b0 *
0)
b0 (
b0 '
0&
0%
b0 $
b0 #
b0 "
b0 !
$end
#5000
1-
#10000
0-
#15000
1-
#20000
0-
#25000
1-
#30000
0-
#35000
1.
1-
#40000
0-
#45000
1-
#46000
b10001 V
b0 U
b100 >
b1101111011101010111010000100000011000010111000001101111011100110010000001110010011001010111001101100101011101000010000000100000 W
b0 X
b0 Y
b1 Z
#50000
0-
#55000
1R
1%
1O
1+
13
17
b1111 6
b1111 B
b10001 5
b10001 A
12
1-
#60000
0-
#65000
1)
b10001 $
b10001 D
b10001 P
0R
0O
0%
0+
07
02
1-
#70000
0-
#75000
0)
1-
#80000
0-
#85000
03
1-
#86000
b100010 V
b100 U
b101 >
b1101111011101010111010000100000011000010111000001101111011100110010000001100101011100110110001101110010011010010111010001100001 W
b10001 X
b10001 Y
b10 Z
#90000
0-
#95000
1R
1%
1O
b100 N
1+
13
17
b100010 5
b100010 A
12
b100 1
b100 @
1-
#100000
0-
#105000
1)
b100010 #
b100010 F
b100010 Q
0R
0O
0%
0+
07
02
1-
#110000
0-
#115000
0)
1-
#120000
0-
#125000
03
1-
#126000
b110011 "
b110011 H
b110011 ;
b110011 G
b110 >
b100010 X
b100010 Y
b11 Z
#130000
0-
#135000
1-
#136000
b1000100 !
b1000100 J
b1000100 <
b1000100 I
b111 >
b1101111011101010111010000100000001111010010000001110010011001010110011100110010010111110110010001101001011011100010000000100000 W
b110011 X
b110011 Y
b100 Z
#140000
0-
#145000
1-
#146000
b0 S
b1000 >
b1101111011101010111010000100000001111010010000001110010011001010110011100110011010111110110010001101001011011100010000000100000 W
b1000100 X
b1000100 Y
b101 Z
#150000
0-
#155000
b10001 (
b10001 L
1&
1,
14
10
1-
#160000
0-
#165000
0&
0,
b10001 T
00
1-
#170000
0-
#175000
04
1-
#176000
b100 S
b1010 >
b1001111010010110100000101011001001000000111001001100101011001110011000000100000001000000010000000100000001000000010000000100000 W
b0 X
b0 Y
b110 Z
b10001 8
#180000
0-
#185000
b100010 (
b100010 L
1&
1,
14
10
b100 /
b100 ?
1-
#190000
0-
#195000
0&
0,
b100010 T
00
1-
#200000
0-
#205000
04
1-
#206000
b1000 S
b1100 >
b1001111010010110100000101011001001000000111001001100101011001110011000100100000001000000010000000100000001000000010000000100000 W
b0 X
b0 Y
b111 Z
b100010 8
#210000
0-
#215000
b110011 (
b110011 L
1&
1,
14
10
b1000 /
b1000 ?
1-
#220000
0-
#225000
0&
0,
b110011 T
00
1-
#230000
0-
#235000
04
1-
#236000
b1100 S
b1110 >
b1001111010010110100000101011001001000000111001001100101011001110011001000100000001000000010000000100000001000000010000000100000 W
b0 X
b0 Y
b1000 Z
b110011 8
#240000
0-
#245000
b1000100 (
b1000100 L
1&
1,
14
10
b1100 /
b1100 ?
1-
#250000
0-
#255000
0&
0,
b1000100 T
00
1-
#260000
0-
#265000
04
1-
#266000
b11011110101011011011111011101111 V
b1000 U
b10100 >
b1101111011101010111010000100000001000000010000000100000001000000010000000100000001000000010000000100000001000000010000000100000 W
b1000100 X
b1000100 Y
b1010 Z
b1000100 8
#270000
0-
#275000
1R
1%
1O
b1000 N
1+
13
17
b11011110101011011011111011101111 5
b11011110101011011011111011101111 A
12
b1000 1
b1000 @
1-
#280000
0-
#285000
1)
0R
0O
0%
0+
07
02
1-
#290000
0-
#295000
0)
1-
#300000
0-
#305000
03
1-
#310000
0-
#315000
1-
#316000
b11001010111111101011101010111110 V
b1100 U
b10101 >
b1100001011011100111010001100101011011010010000001110010011001010110011100110010010111110110010001101001011011100010000000100000 W
b110011 X
b110011 Y
b1011 Z
#320000
0-
#325000
1R
1%
1O
b1100 N
1+
13
17
b11001010111111101011101010111110 5
b11001010111111101011101010111110 A
12
b1100 1
b1100 @
1-
#330000
0-
#335000
1)
0R
0O
0%
0+
07
02
1-
#340000
0-
#345000
0)
1-
#350000
0-
#355000
03
1-
#360000
0-
#365000
1-
#366000
b10110 >
b1100001011011100111010001100101011011010010000001110010011001010110011100110011010111110110010001101001011011100010000000100000 W
b1000100 X
b1000100 Y
b1100 Z
