Ex_25_05/ex02/ex2_cache.v
module cache_contadores (
    input  wire        clk,
    input  wire        reset,
    input  wire        read,
    input  wire [4:0]  address,
    input  wire [7:0]  mem_data,
    output reg  [7:0]  cache_data,
    output reg         hit,
    output reg         miss,
    output reg  [7:0]  hit_count,
    output reg  [7:0]  miss_count
);

    // Memória interna da cache
    reg        valid     [0:7];  // bits de validade
    reg [1:0]  tag_array [0:7];  // tags armazenadas (2 bits)
    reg [7:0]  data_array[0:7];  // dados armazenados

    // Divisão do endereço: 5 bits → TAG[4:3] | ÍNDICE[2:0]
    wire [1:0] tag   = address[4:3];
    wire [2:0] index = address[2:0];

    integer i;

    always @(posedge clk or posedge reset) begin
        if (reset) begin
            for (i = 0; i < 8; i = i + 1)
                valid[i] <= 1'b0;
            hit        <= 1'b0;
            miss       <= 1'b0;
            hit_count  <= 8'd0;
            miss_count <= 8'd0;
            cache_data <= 8'h00;
        end
        else if (read) begin
            if (valid[index] && (tag_array[index] == tag)) begin
                // HIT
                hit        <= 1'b1;
                miss       <= 1'b0;
                cache_data <= data_array[index];
                hit_count  <= hit_count + 1;
            end
            else begin
                // MISS — substitui o conteúdo da posição
                hit              <= 1'b0;
                miss             <= 1'b1;
                valid[index]     <= 1'b1;
                tag_array[index] <= tag;
                data_array[index]<= mem_data;
                cache_data       <= mem_data;
                miss_count       <= miss_count + 1;
            end
        end
        else begin
            hit  <= 1'b0;
            miss <= 1'b0;
        end
    end

endmodule

Ex_25_05/ex02/tb_ex2.v

`timescale 1ns/1ps

module tb_cache_contadores;

    // Sinais
    reg        clk;
    reg        reset;
    reg        read;
    reg  [4:0] address;
    reg  [7:0] mem_data;
    wire [7:0] cache_data;
    wire       hit;
    wire       miss;
    wire [7:0] hit_count;
    wire [7:0] miss_count;

    // Instancia o módulo
    cache_contadores dut (
        .clk        (clk),
        .reset      (reset),
        .read       (read),
        .address    (address),
        .mem_data   (mem_data),
        .cache_data (cache_data),
        .hit        (hit),
        .miss       (miss),
        .hit_count  (hit_count),
        .miss_count (miss_count)
    );

    // Clock: período de 10 ns
    initial clk = 0;
    always #5 clk = ~clk;

    integer num_acesso;

    task acesso;
        input [4:0] addr;
        input [7:0] dado;
        begin
            num_acesso = num_acesso + 1;
            address    = addr;
            mem_data   = dado;
            read       = 1;
            @(posedge clk); #1;
            $display("Acesso %0d | End: %b | Tag: %b | Idx: %b | %s | Dado: %h | Hits: %0d | Miss: %0d",
                     num_acesso, addr, addr[4:3], addr[2:0],
                     hit ? "HIT " : "MISS",
                     cache_data,
                     hit_count, miss_count);
            read = 0;
            @(posedge clk); #1;
        end
    endtask

    initial begin
        // Geração do arquivo de ondas — caminho absoluto para Windows
        $dumpfile("C:/Users/jones/Desktop/Projectos/ex02/wave_ex2.vcd");
        $dumpvars(0, tb_cache_contadores);

        num_acesso = 0;

        $display("===========================================================");
        $display("  Exercicio 2 - Cache com Contadores de Hit e Miss");
        $display("  8 blocos | Endereco 5 bits | TAG[4:3] | INDICE[2:0]");
        $display("===========================================================");

        // Reset
        reset = 1; read = 0; address = 0; mem_data = 0;
        @(posedge clk); #1;
        reset = 0;
        @(posedge clk); #1;

        acesso(5'b10110, 8'hA1);  // 1: MISS
        acesso(5'b11010, 8'hB2);  // 2: MISS
        acesso(5'b10110, 8'hA1);  // 3: HIT
        acesso(5'b11010, 8'hB2);  // 4: HIT
        acesso(5'b10000, 8'hC3);  // 5: MISS
        acesso(5'b00011, 8'hD4);  // 6: MISS
        acesso(5'b10000, 8'hC3);  // 7: HIT
        acesso(5'b10010, 8'hE5);  // 8: MISS (conflito indice 010)
        acesso(5'b10000, 8'hC3);  // 9: HIT

        $display("===========================================================");
        $display("  Total de acessos : %0d", num_acesso);
        $display("  Hits             : %0d", hit_count);
        $display("  Misses           : %0d", miss_count);
        $display("  Taxa de acerto   : 4/9 = 44.44%%");
        $display("===========================================================");
        $finish;
    end

endmodule

Ex_25_05/ex02/wave_ex2.vcd
$date
	Sat May 30 20:25:41 2026
$end
$version
	Icarus Verilog
$end
$timescale
	1ps
$end
$scope module tb_cache_contadores $end
$var wire 8 ! miss_count [7:0] $end
$var wire 1 " miss $end
$var wire 8 # hit_count [7:0] $end
$var wire 1 $ hit $end
$var wire 8 % cache_data [7:0] $end
$var reg 5 & address [4:0] $end
$var reg 1 ' clk $end
$var reg 8 ( mem_data [7:0] $end
$var reg 1 ) read $end
$var reg 1 * reset $end
$var integer 32 + num_acesso [31:0] $end
$scope module dut $end
$var wire 5 , address [4:0] $end
$var wire 1 ' clk $end
$var wire 8 - mem_data [7:0] $end
$var wire 1 ) read $end
$var wire 1 * reset $end
$var wire 2 . tag [1:0] $end
$var wire 3 / index [2:0] $end
$var reg 8 0 cache_data [7:0] $end
$var reg 1 $ hit $end
$var reg 8 1 hit_count [7:0] $end
$var reg 1 " miss $end
$var reg 8 2 miss_count [7:0] $end
$var integer 32 3 i [31:0] $end
$upscope $end
$scope task acesso $end
$var reg 5 4 addr [4:0] $end
$var reg 8 5 dado [7:0] $end
$upscope $end
$upscope $end
$enddefinitions $end
$comment Show the parameter values. $end
$dumpall
$end
#0
$dumpvars
bx 5
bx 4
b1000 3
b0 2
b0 1
b0 0
b0 /
b0 .
b0 -
b0 ,
b0 +
1*
0)
b0 (
0'
b0 &
b0 %
0$
b0 #
0"
b0 !
$end
#5000
b1000 3
1'
#6000
0*
#10000
0'
#15000
1'
#16000
b10 .
b110 /
1)
b10100001 (
b10100001 -
b10110 &
b10110 ,
b1 +
b10100001 5
b10110 4
#20000
0'
#25000
b1 !
b1 2
b10100001 %
b10100001 0
1"
1'
#26000
0)
#30000
0'
#35000
0"
1'
#36000
b11 .
b10 /
1)
b10110010 (
b10110010 -
b11010 &
b11010 ,
b10 +
b10110010 5
b11010 4
#40000
0'
#45000
b10 !
b10 2
b10110010 %
b10110010 0
1"
1'
#46000
0)
#50000
0'
#55000
0"
1'
#56000
b10 .
b110 /
1)
b10100001 (
b10100001 -
b10110 &
b10110 ,
b11 +
b10100001 5
b10110 4
#60000
0'
#65000
b1 #
b1 1
b10100001 %
b10100001 0
1$
1'
#66000
0)
#70000
0'
#75000
0$
1'
#76000
b11 .
b10 /
1)
b10110010 (
b10110010 -
b11010 &
b11010 ,
b100 +
b10110010 5
b11010 4
#80000
0'
#85000
b10 #
b10 1
b10110010 %
b10110010 0
1$
1'
#86000
0)
#90000
0'
#95000
0$
1'
#96000
b10 .
b0 /
1)
b11000011 (
b11000011 -
b10000 &
b10000 ,
b101 +
b11000011 5
b10000 4
#100000
0'
#105000
b11 !
b11 2
b11000011 %
b11000011 0
1"
1'
#106000
0)
#110000
0'
#115000
0"
1'
#116000
b0 .
b11 /
1)
b11010100 (
b11010100 -
b11 &
b11 ,
b110 +
b11010100 5
b11 4
#120000
0'
#125000
b100 !
b100 2
b11010100 %
b11010100 0
1"
1'
#126000
0)
#130000
0'
#135000
0"
1'
#136000
b10 .
b0 /
1)
b11000011 (
b11000011 -
b10000 &
b10000 ,
b111 +
b11000011 5
b10000 4
#140000
0'
#145000
b11 #
b11 1
b11000011 %
b11000011 0
1$
1'
#146000
0)
#150000
0'
#155000
0$
1'
#156000
b10 /
1)
b11100101 (
b11100101 -
b10010 &
b10010 ,
b1000 +
b11100101 5
b10010 4
#160000
0'
#165000
b101 !
b101 2
b11100101 %
b11100101 0
1"
1'
#166000
0)
#170000
0'
#175000
0"
1'
#176000
b0 /
1)
b11000011 (
b11000011 -
b10000 &
b10000 ,
b1001 +
b11000011 5
b10000 4
#180000
0'
#185000
b100 #
b100 1
b11000011 %
b11000011 0
1$
1'
#186000
0)
#190000
0'
#195000
0$
1'
