Ex_25_05/ex01/ex1_cache.v
module cache_simples (
    input  wire        clk,
    input  wire        reset,
    input  wire        read,
    input  wire [3:0]  address,
    input  wire [7:0]  mem_data,
    output reg  [7:0]  cache_data,
    output reg         hit,
    output reg         miss
);

    // Memória interna da cache
    reg        valid     [0:3];  // bits de validade
    reg [1:0]  tag_array [0:3];  // tags armazenadas
    reg [7:0]  data_array[0:3];  // dados armazenados

    // Divisão do endereço
    wire [1:0] tag   = address[3:2];  // bits mais significativos
    wire [1:0] index = address[1:0];  // bits menos significativos

    integer i;

    always @(posedge clk or posedge reset) begin
        if (reset) begin
            // Zera todos os bits de validade
            for (i = 0; i < 4; i = i + 1)
                valid[i] <= 1'b0;
            hit        <= 1'b0;
            miss       <= 1'b0;
            cache_data <= 8'h00;
        end
        else if (read) begin
            if (valid[index] && (tag_array[index] == tag)) begin
                // HIT — dado encontrado na cache
                hit        <= 1'b1;
                miss       <= 1'b0;
                cache_data <= data_array[index];
            end
            else begin
                // MISS — carrega dado da memória principal
                hit              <= 1'b0;
                miss             <= 1'b1;
                valid[index]     <= 1'b1;
                tag_array[index] <= tag;
                data_array[index]<= mem_data;
                cache_data       <= mem_data;
            end
        end
        else begin
            hit  <= 1'b0;
            miss <= 1'b0;
        end
    end

endmodule

Ex_25_05/ex01/tb_ex1.v
`timescale 1ns/1ps

module tb_cache_simples;

    // Sinais
    reg        clk;
    reg        reset;
    reg        read;
    reg  [3:0] address;
    reg  [7:0] mem_data;
    wire [7:0] cache_data;
    wire       hit;
    wire       miss;

    // Instancia o módulo
    cache_simples dut (
        .clk        (clk),
        .reset      (reset),
        .read       (read),
        .address    (address),
        .mem_data   (mem_data),
        .cache_data (cache_data),
        .hit        (hit),
        .miss       (miss)
    );

    // Clock: período de 10 ns
    initial clk = 0;
    always #5 clk = ~clk;

    // Tarefa auxiliar para exibir resultado
    task acesso;
        input [3:0]  addr;
        input [7:0]  dado;
        input [7:0]  acesso_num;
        begin
            address  = addr;
            mem_data = dado;
            read     = 1;
            @(posedge clk); #1;
            $display("Acesso %0d | Endereço: %b | Tag: %b | Índice: %b | Resultado: %s | Dado: %h",
                     acesso_num, addr, addr[3:2], addr[1:0],
                     hit ? "HIT " : "MISS",
                     cache_data);
            read = 0;
            @(posedge clk); #1;
        end
    endtask

    initial begin
        // ── Geração do arquivo de ondas ──
        $dumpfile("wave.vcd");
        $dumpvars(0, tb_cache_simples);

        $display("=======================================================");
        $display("  Exercício 1 — Cache Mapeada Diretamente Simples");
        $display("  4 blocos | Endereço 4 bits | TAG[3:2] | ÍNDICE[1:0]");
        $display("=======================================================");

        // Reset inicial
        reset = 1; read = 0; address = 0; mem_data = 0;
        @(posedge clk); #1;
        reset = 0;
        @(posedge clk); #1;

        $display("Acesso | Endereço | Tag | Índice | Resultado | Dado");
        $display("-------------------------------------------------------");

        acesso(4'b1011, 8'hA1, 1);   // 1: MISS  (1ª vez, cache vazia)
        acesso(4'b1011, 8'hA1, 2);   // 2: HIT   (mesmo endereço)
        acesso(4'b0011, 8'hB2, 3);   // 3: MISS  (mesmo índice, tag diferente)
        acesso(4'b0011, 8'hB2, 4);   // 4: HIT   (mesmo endereço)
        acesso(4'b1011, 8'hA1, 5);   // 5: MISS  (conflito: tag 10 foi substituída por 00)

        $display("=======================================================");
        $display("Simulação concluída.");
        $finish;
    end

endmodule

Ex_25_05/ex01/wave.vcd
$date
	Sat May 30 19:21:48 2026
$end
$version
	Icarus Verilog
$end
$timescale
	1ps
$end
$scope module tb_cache_simples $end
$var wire 1 ! miss $end
$var wire 1 " hit $end
$var wire 8 # cache_data [7:0] $end
$var reg 4 $ address [3:0] $end
$var reg 1 % clk $end
$var reg 8 & mem_data [7:0] $end
$var reg 1 ' read $end
$var reg 1 ( reset $end
$scope module dut $end
$var wire 4 ) address [3:0] $end
$var wire 1 % clk $end
$var wire 8 * mem_data [7:0] $end
$var wire 1 ' read $end
$var wire 1 ( reset $end
$var wire 2 + tag [1:0] $end
$var wire 2 , index [1:0] $end
$var reg 8 - cache_data [7:0] $end
$var reg 1 " hit $end
$var reg 1 ! miss $end
$var integer 32 . i [31:0] $end
$upscope $end
$scope task acesso $end
$var reg 8 / acesso_num [7:0] $end
$var reg 4 0 addr [3:0] $end
$var reg 8 1 dado [7:0] $end
$upscope $end
$upscope $end
$enddefinitions $end
$comment Show the parameter values. $end
$dumpall
$end
#0
$dumpvars
bx 1
bx 0
bx /
b100 .
b0 -
b0 ,
b0 +
b0 *
b0 )
1(
0'
b0 &
0%
b0 $
b0 #
0"
0!
$end
#5000
b100 .
1%
#6000
0(
#10000
0%
#15000
1%
#16000
b10 +
b11 ,
1'
b10100001 &
b10100001 *
b1011 $
b1011 )
b1 /
b10100001 1
b1011 0
#20000
0%
#25000
b10100001 #
b10100001 -
1!
1%
#26000
0'
#30000
0%
#35000
0!
1%
#36000
1'
b10 /
#40000
0%
#45000
1"
1%
#46000
0'
#50000
0%
#55000
0"
1%
#56000
b0 +
1'
b10110010 &
b10110010 *
b11 $
b11 )
b11 /
b10110010 1
b11 0
#60000
0%
#65000
b10110010 #
b10110010 -
1!
1%
#66000
0'
#70000
0%
#75000
0!
1%
#76000
1'
b100 /
#80000
0%
#85000
1"
1%
#86000
0'
#90000
0%
#95000
0"
1%
#96000
b10 +
1'
b10100001 &
b10100001 *
b1011 $
b1011 )
b101 /
b10100001 1
b1011 0
#100000
0%
#105000
b10100001 #
b10100001 -
1!
1%
#106000
0'
#110000
0%
#115000
0!
1%
